dinomov.v
module dino_mov(
    input clk,
    input reset,
    input jump_button,
    output reg [15:0] grid //[15:8]=row1, [7:0]=row0
);
reg [2:0] col;
reg row;
reg [1:0]jump_counter;
always @(posedge clk or posedge reset) begin 
    if (reset) begin
    row<=0;
    jump_counter=0;
    end
    else begin
            if (jump_button && row == 0) begin
                // Start jump
                row <= 1;
                jump_counter <= 2; // stays in air for 2 clock cycles ie 20ns
            end 
            //ignore the jump initiated when row==1
            else if (jump_counter!=0)begin
                jump_counter <= jump_counter - 1;
                if (jump_counter == 1)
                    row <= 0; // fall back down
            end
    end
    //row<=~row;// this is making the dino jump up or down only when i push jump i want it to jump then after some clk
    //cycles come back down again
    //Idea:
//When jump_button is pressed, set row = 1.

//Start a counter (e.g., 3 or 4 cycles).

//After the counter expires, reset row = 0.


end

always @(*) begin
        grid = 16'b0;  // clear grid
        if (row == 0)
            grid[7] = 1'b1;       // row 0, column 0 (down row)
        else
            grid[15] = 1'b1;       // row 1, column 0 (up row)
    end
endmodule

dinomovtb.v
module dino_move_tb();
reg clk;
reg reset;
reg jump_button;
wire [15:0] grid;

dino_mov dut (
        .clk(clk),
        .reset(reset),
        .jump_button(jump_button),
        .grid(grid)
    );

    // Clock generation
    initial clk = 0;
    always #10 clk = ~clk;

    initial begin
        // Initialize
        reset = 1;
        jump_button = 0;

        #20 reset = 0;

        // Simulate jump at different times
        #200 jump_button = 1;//for 50ns the jump button remains 1
        #70  jump_button = 0;

        #300 jump_button = 1;
        #70  jump_button = 0;

        #200  jump_button = 1;
        #90  jump_button = 0;

        #1000 $finish;
    end

    initial begin
    $dumpfile("dinomov.vcd");
    $dumpvars(0, dino_move_tb);  
    $monitor("time =%d, jump=%b, up=%b \n down=%b", $time,jump_button, grid[15:8], grid[7:0]);
    end
  
    endmodule

dinomov.vcd
$date
	Mon Jun 23 00:54:43 2025
$end
$version
	Icarus Verilog
$end
$timescale
	1s
$end
$scope module dino_move_tb $end
$var wire 16 ! grid [15:0] $end
$var reg 1 " clk $end
$var reg 1 # jump_button $end
$var reg 1 $ reset $end
$scope module dut $end
$var wire 1 " clk $end
$var wire 1 # jump_button $end
$var wire 1 $ reset $end
$var reg 16 % grid [15:0] $end
$var reg 2 & jump_counter [1:0] $end
$var reg 1 ' row $end
$upscope $end
$upscope $end
$enddefinitions $end
$comment Show the parameter values. $end
$dumpall
$end
#0
$dumpvars
0'
b0 &
b10000000 %
1$
0#
0"
b10000000 !
$end
#10
1"
#20
0"
0$
#30
1"
#40
0"
#50
1"
#60
0"
#70
1"
#80
0"
#90
1"
#100
0"
#110
1"
#120
0"
#130
1"
#140
0"
#150
1"
#160
0"
#170
1"
#180
0"
#190
1"
#200
0"
#210
1"
#220
0"
1#
#230
b1000000000000000 !
b1000000000000000 %
b10 &
1'
1"
#240
0"
#250
b1 &
1"
#260
0"
#270
b10000000 !
b10000000 %
0'
b0 &
1"
#280
0"
#290
1"
0#
#300
0"
#310
1"
#320
0"
#330
1"
#340
0"
#350
1"
#360
0"
#370
1"
#380
0"
#390
1"
#400
0"
#410
1"
#420
0"
#430
1"
#440
0"
#450
1"
#460
0"
#470
1"
#480
0"
#490
1"
#500
0"
#510
1"
#520
0"
#530
1"
#540
0"
#550
1"
#560
0"
#570
1"
#580
0"
#590
b1000000000000000 !
b1000000000000000 %
b10 &
1'
1"
1#
#600
0"
#610
b1 &
1"
#620
0"
#630
b10000000 !
b10000000 %
0'
b0 &
1"
#640
0"
#650
b1000000000000000 !
b1000000000000000 %
b10 &
1'
1"
#660
0"
0#
#670
b1 &
1"
#680
0"
#690
b10000000 !
b10000000 %
0'
b0 &
1"
#700
0"
#710
1"
#720
0"
#730
1"
#740
0"
#750
1"
#760
0"
#770
1"
#780
0"
#790
1"
#800
0"
#810
1"
#820
0"
#830
1"
#840
0"
#850
1"
#860
0"
1#
#870
b1000000000000000 !
b1000000000000000 %
b10 &
1'
1"
#880
0"
#890
b1 &
1"
#900
0"
#910
b10000000 !
b10000000 %
0'
b0 &
1"
#920
0"
#930
b1000000000000000 !
b1000000000000000 %
b10 &
1'
1"
#940
0"
#950
b1 &
1"
0#
#960
0"
#970
b10000000 !
b10000000 %
0'
b0 &
1"
