obstaclegpt.v
module obstacle_gen (
    input clk,
    input reset,
    input tick,                // slow clock for movement
    output reg [7:0] down      // obstacle row
);

    reg [7:0] obs_shift;       // internal shift register
    reg [1:0] spacing;         // spacing counter (counts up to 3)

    wire [1:0] rand = spacing ^ obs_shift[1:0];  // simple pseudo-random bits

    always @(posedge clk or posedge reset) begin
        if (reset) begin
            obs_shift <= 8'b0;
            spacing <= 2'd0;
            down <= 8'b0;
        end else if (tick) begin
            if (spacing == 2'd3) begin
                spacing <= 0;
                // inject new obstacle
                case (rand)
                    2'b00: obs_shift <= {obs_shift[6:0], 1'b1};        // 1-bit obstacle
                    2'b01: obs_shift <= {obs_shift[5:0], 2'b11};       // 2-bit obstacle
                    default: obs_shift <= {obs_shift[6:0], 1'b0};      // no obstacle (rare case)
                endcase
            end else begin
                spacing <= spacing + 1;
                obs_shift <= {obs_shift[6:0], 1'b0};  // shift left with blank
            end
            down <= obs_shift;
        end
    end

endmodule

obstaclegptb.v
`timescale 1ns/1ps

module obstacle_gen_tb;

    reg clk;
    reg reset;
    reg tick;
    wire [7:0] down;

    obstacle_gen uut (
        .clk(clk),
        .reset(reset),
        .tick(tick),
        .down(down)
    );

    // Clock generation
    initial clk = 0;
    always #5 clk = ~clk;  // 100MHz clock (10ns period)

    initial begin
        $dumpfile("obstaclegpt.vcd");
        $dumpvars(0, obstacle_gen_tb);

        // Initial values
        tick = 0;
        reset = 1;

        #20 reset = 0;

        // Stimulate 50 ticks
        repeat (50) begin
            #10 tick = 1;
            #10 tick = 0;
            $display("T=%0t | down = %b", $time, down);
        end

        $finish;
    end

endmodule

obstaclegpt.vcd
$date
	Fri Jun 13 20:44:22 2025
$end
$version
	Icarus Verilog
$end
$timescale
	1ps
$end
$scope module obstacle_gen_tb $end
$var wire 8 ! down [7:0] $end
$var reg 1 " clk $end
$var reg 1 # reset $end
$var reg 1 $ tick $end
$scope module uut $end
$var wire 1 " clk $end
$var wire 2 % rand [1:0] $end
$var wire 1 # reset $end
$var wire 1 $ tick $end
$var reg 8 & down [7:0] $end
$var reg 8 ' obs_shift [7:0] $end
$var reg 2 ( spacing [1:0] $end
$upscope $end
$upscope $end
$enddefinitions $end
$comment Show the parameter values. $end
$dumpall
$end
#0
$dumpvars
b0 (
b0 '
b0 &
b0 %
0$
1#
0"
b0 !
$end
#5000
1"
#10000
0"
#15000
1"
#20000
0"
0#
#25000
1"
#30000
0"
1$
#35000
b1 %
b1 (
1"
#40000
0"
0$
#45000
1"
#50000
0"
1$
#55000
b10 %
b10 (
1"
#60000
0"
0$
#65000
1"
#70000
0"
1$
#75000
b11 %
b11 (
1"
#80000
0"
0$
#85000
1"
#90000
0"
1$
#95000
b0 %
b0 (
1"
#100000
0"
0$
#105000
1"
#110000
0"
1$
#115000
b1 %
b1 (
1"
#120000
0"
0$
#125000
1"
#130000
0"
1$
#135000
b10 %
b10 (
1"
#140000
0"
0$
#145000
1"
#150000
0"
1$
#155000
b11 %
b11 (
1"
#160000
0"
0$
#165000
1"
#170000
0"
1$
#175000
b0 %
b0 (
1"
#180000
0"
0$
#185000
1"
#190000
0"
1$
#195000
b1 %
b1 (
1"
#200000
0"
0$
#205000
1"
#210000
0"
1$
#215000
b10 %
b10 (
1"
#220000
0"
0$
#225000
1"
#230000
0"
1$
#235000
b11 %
b11 (
1"
#240000
0"
0$
#245000
1"
#250000
0"
1$
#255000
b0 %
b0 (
1"
#260000
0"
0$
#265000
1"
#270000
0"
1$
#275000
b1 %
b1 (
1"
#280000
0"
0$
#285000
1"
#290000
0"
1$
#295000
b10 %
b10 (
1"
#300000
0"
0$
#305000
1"
#310000
0"
1$
#315000
b11 %
b11 (
1"
#320000
0"
0$
#325000
1"
#330000
0"
1$
#335000
b0 %
b0 (
1"
#340000
0"
0$
#345000
1"
#350000
0"
1$
#355000
b1 %
b1 (
1"
#360000
0"
0$
#365000
1"
#370000
0"
1$
#375000
b10 %
b10 (
1"
#380000
0"
0$
#385000
1"
#390000
0"
1$
#395000
b11 %
b11 (
1"
#400000
0"
0$
#405000
1"
#410000
0"
1$
#415000
b0 %
b0 (
1"
#420000
0"
0$
#425000
1"
#430000
0"
1$
#435000
b1 %
b1 (
1"
#440000
0"
0$
#445000
1"
#450000
0"
1$
#455000
b10 %
b10 (
1"
#460000
0"
0$
#465000
1"
#470000
0"
1$
#475000
b11 %
b11 (
1"
#480000
0"
0$
#485000
1"
#490000
0"
1$
#495000
b0 %
b0 (
1"
#500000
0"
0$
#505000
1"
#510000
0"
1$
#515000
b1 %
b1 (
1"
#520000
0"
0$
#525000
1"
#530000
0"
1$
#535000
b10 %
b10 (
1"
#540000
0"
0$
#545000
1"
#550000
0"
1$
#555000
b11 %
b11 (
1"
#560000
0"
0$
#565000
1"
#570000
0"
1$
#575000
b0 %
b0 (
1"
#580000
0"
0$
#585000
1"
#590000
0"
1$
#595000
b1 %
b1 (
1"
#600000
0"
0$
#605000
1"
#610000
0"
1$
#615000
b10 %
b10 (
1"
#620000
0"
0$
#625000
1"
#630000
0"
1$
#635000
b11 %
b11 (
1"
#640000
0"
0$
#645000
1"
#650000
0"
1$
#655000
b0 %
b0 (
1"
#660000
0"
0$
#665000
1"
#670000
0"
1$
#675000
b1 %
b1 (
1"
#680000
0"
0$
#685000
1"
#690000
0"
1$
#695000
b10 %
b10 (
1"
#700000
0"
0$
#705000
1"
#710000
0"
1$
#715000
b11 %
b11 (
1"
#720000
0"
0$
#725000
1"
#730000
0"
1$
#735000
b0 %
b0 (
1"
#740000
0"
0$
#745000
1"
#750000
0"
1$
#755000
b1 %
b1 (
1"
#760000
0"
0$
#765000
1"
#770000
0"
1$
#775000
b10 %
b10 (
1"
#780000
0"
0$
#785000
1"
#790000
0"
1$
#795000
b11 %
b11 (
1"
#800000
0"
0$
#805000
1"
#810000
0"
1$
#815000
b0 %
b0 (
1"
#820000
0"
0$
#825000
1"
#830000
0"
1$
#835000
b1 %
b1 (
1"
#840000
0"
0$
#845000
1"
#850000
0"
1$
#855000
b10 %
b10 (
1"
#860000
0"
0$
#865000
1"
#870000
0"
1$
#875000
b11 %
b11 (
1"
#880000
0"
0$
#885000
1"
#890000
0"
1$
#895000
b0 %
b0 (
1"
#900000
0"
0$
#905000
1"
#910000
0"
1$
#915000
b1 %
b1 (
1"
#920000
0"
0$
#925000
1"
#930000
0"
1$
#935000
b10 %
b10 (
1"
#940000
0"
0$
#945000
1"
#950000
0"
1$
#955000
b11 %
b11 (
1"
#960000
0"
0$
#965000
1"
#970000
0"
1$
#975000
b0 %
b0 (
1"
#980000
0"
0$
#985000
1"
#990000
0"
1$
#995000
b1 %
b1 (
1"
#1000000
0"
0$
#1005000
1"
#1010000
0"
1$
#1015000
b10 %
b10 (
1"
#1020000
0"
0$
